pygltflib/__init__.py
pygltflib/utils.py
pygltflib/validator.py
pygltflib_py37-1.14.7.dist-info/LICENSE
pygltflib_py37-1.14.7.dist-info/METADATA
pygltflib_py37-1.14.7.dist-info/WHEEL
pygltflib_py37-1.14.7.dist-info/top_level.txt
pygltflib_py37-1.14.7.dist-info/RECORD
