Metadata-Version: 2.1
Name: pygltflib-py37
Version: 1.14.7
Summary: A simple fix for pygltflib to work with Python 3.7+ on cloud environments.
Home-page: https://gitlab.com/dodgyville/pygltflib
Author: Luke Miller
Author-email: dodgyville@gmail.com
License: UNKNOWN
Platform: UNKNOWN
Classifier: Programming Language :: Python :: 3
Classifier: License :: OSI Approved :: MIT License
Classifier: Operating System :: OS Independent
Requires-Python: >=3.6
License-File: LICENSE
Requires-Dist: dataclasses-json (>=0.0.25)
Requires-Dist: deprecated
Requires-Dist: dataclasses ; python_version >= "3.6" and python_version < "3.7"
